{"trial_id": "079", "hyperparameters": {"space": [{"class_name": "Float", "config": {"name": "dropout1", "default": 0.0, "conditions": [], "min_value": 0.0, "max_value": 0.8, "step": 0.1, "sampling": "linear"}}, {"class_name": "Float", "config": {"name": "dropout2", "default": 0.0, "conditions": [], "min_value": 0.0, "max_value": 0.8, "step": 0.1, "sampling": "linear"}}, {"class_name": "Float", "config": {"name": "dropout3", "default": 0.0, "conditions": [], "min_value": 0.0, "max_value": 0.8, "step": 0.1, "sampling": "linear"}}, {"class_name": "Boolean", "config": {"name": "batchnorm", "default": false, "conditions": []}}], "values": {"dropout1": 0.2, "dropout2": 0.1, "dropout3": 0.4, "batchnorm": true}}, "metrics": {"metrics": {"acc": {"direction": "max", "observations": [{"value": [0.9899304906527201], "step": 4}]}, "loss": {"direction": "min", "observations": [{"value": [0.033808170507351555], "step": 4}]}, "val_acc": {"direction": "max", "observations": [{"value": [0.628853976726532], "step": 4}]}, "val_loss": {"direction": "min", "observations": [{"value": [2.1329362193743386], "step": 4}]}}}, "score": 0.628853976726532, "best_step": 4, "status": "COMPLETED", "message": null}